{
	"info": {
		"_postman_id": "5f7c9e30-fa48-4a47-9d18-eddb312e01fe",
		"name": "SharingVision",
		"schema": "https://schema.getpostman.com/json/collection/v2.1.0/collection.json"
	},
	"item": [
		{
			"name": "Post new article",
			"request": {
				"method": "POST",
				"header": [],
				"body": {
					"mode": "raw",
					"raw": "{\r\n    \"title\": \"IP Datagrams\",\r\n    \"content\": \"The IP layer provides a connectionless and unreliable delivery system. It considers each datagram independently of the others. Any association between datagrams must be supplied by the higher layers.\",\r\n    \"category\":\"Networking\",\r\n    \"status\":\"New\"\r\n}",
					"options": {
						"raw": {
							"language": "json"
						}
					}
				},
				"url": {
					"raw": "http://127.0.0.1:5000/article/",
					"protocol": "http",
					"host": [
						"127",
						"0",
						"0",
						"1"
					],
					"port": "5000",
					"path": [
						"article",
						""
					]
				}
			},
			"response": []
		},
		{
			"name": "Get article by id",
			"request": {
				"method": "GET",
				"header": [],
				"url": {
					"raw": "http://127.0.0.1:5000/article/4",
					"protocol": "http",
					"host": [
						"127",
						"0",
						"0",
						"1"
					],
					"port": "5000",
					"path": [
						"article",
						"4"
					]
				}
			},
			"response": []
		},
		{
			"name": "Post new article part-2",
			"request": {
				"method": "POST",
				"header": [],
				"body": {
					"mode": "raw",
					"raw": "{\r\n    \"title\": \"Looking into scope\",\r\n    \"content\": \"When a variable is declared, it comes into scope, or to put it another way, the variable becomes visible.\",\r\n    \"category\":\"Programming\",\r\n    \"status\":\"New\"\r\n}",
					"options": {
						"raw": {
							"language": "json"
						}
					}
				},
				"url": {
					"raw": "http://127.0.0.1:5000/article/",
					"protocol": "http",
					"host": [
						"127",
						"0",
						"0",
						"1"
					],
					"port": "5000",
					"path": [
						"article",
						""
					]
				}
			},
			"response": []
		},
		{
			"name": "Update article",
			"request": {
				"method": "POST",
				"header": [],
				"body": {
					"mode": "raw",
					"raw": "{\r\n    \"title\": \"Connection Oriented\",\r\n    \"content\": \"In a connectionless system, messages are sent independent of each other. Ordinary mail is the analogy.\",\r\n    \"category\":\"Networking\",\r\n    \"status\":\"Update\"\r\n}",
					"options": {
						"raw": {
							"language": "json"
						}
					}
				},
				"url": {
					"raw": "http://127.0.0.1:5000/article/1",
					"protocol": "http",
					"host": [
						"127",
						"0",
						"0",
						"1"
					],
					"port": "5000",
					"path": [
						"article",
						"1"
					]
				}
			},
			"response": []
		},
		{
			"name": "Delete article",
			"request": {
				"method": "DELETE",
				"header": [],
				"url": {
					"raw": "http://127.0.0.1:5000/article/1",
					"protocol": "http",
					"host": [
						"127",
						"0",
						"0",
						"1"
					],
					"port": "5000",
					"path": [
						"article",
						"1"
					]
				}
			},
			"response": []
		},
		{
			"name": "Post new article part-3",
			"request": {
				"method": "POST",
				"header": [],
				"body": {
					"mode": "raw",
					"raw": "{\r\n    \"title\": \"True or false\",\r\n    \"content\": \"True and false are Boolean values, so named after 19th century mathematician George Boole. \",\r\n    \"category\":\"Programming\",\r\n    \"status\":\"New\"\r\n}",
					"options": {
						"raw": {
							"language": "json"
						}
					}
				},
				"url": {
					"raw": "http://127.0.0.1:5000/article/",
					"protocol": "http",
					"host": [
						"127",
						"0",
						"0",
						"1"
					],
					"port": "5000",
					"path": [
						"article",
						""
					]
				}
			},
			"response": []
		},
		{
			"name": "Get article with pagination",
			"request": {
				"method": "GET",
				"header": [],
				"url": {
					"raw": "http://127.0.0.1:5000/article/2/2",
					"protocol": "http",
					"host": [
						"127",
						"0",
						"0",
						"1"
					],
					"port": "5000",
					"path": [
						"article",
						"2",
						"2"
					]
				}
			},
			"response": []
		}
	]
}